Workbook
Name Slicer_Category: #N/A
Name Slicer_Device: #N/A
Name Slicer_Region: #N/A
Name Slicer_Year: #N/A

Sheet Trend analysis
B3: Months | C3: Total Quantity | H3: Years | I3: Total Revenue | J3: YoY | N3: Years | O3: Profit
B4: Jan | C4: 370 | H4: 2015 | I4: 782733 | J4: 0 | N4: 2015 | O4: 189119
B5: Feb | C5: 412 | H5: 2016 | I5: 1088845 | J5: 0.39108099 | N5: 2016 | O5: 235509
B6: Mar | C6: 1619 | H6: 2017 | I6: 1481461 | J6: 0.36058025 | N6: 2017 | O6: 374408
B7: Apr | C7: 1368 | H7: 2018 | I7: 2161749 | J7: 0.45920075 | N7: 2018 | O7: 696503
B8: May | C8: 1306 | H8: 2019 | I8: 1512837 | J8: -0.30017916 | N8: 2019 | O8: 622776
B9: Jun | C9: 803 | H9: 2020 | I9: 463262 | J9: -0.6937793 | N9: 2020 | O9: 117038
B10: Jul | C10: 696 | H10: Grand Total | I10: 7490887 | J10: 0.065920137 | N10: Grand Total | O10: 2235353
B11: Aug | C11: 827
B12: Sep | C12: 587
B13: Oct | C13: 1278
B14: Nov | C14: 1188
B15: Dec | C15: 764
B16: Grand Total | C16: 11218

Sheet KPIS
C4: Total Units | D4: Total Units YoY | E4: Total Revenue | F4: Total Revenue YoY | G4: Total Cost | H4: Total Cost YoY | I4: Profit | J4: Profit YoY | K4: Total Customers | L4: Total Customers YoY
C5: 11218 | D5: 0.24161594 | E5: 1088845 | F5: 0.39108099 | G5: 853336 | H5: 0.43752674 | I5: 235509 | J5: 0.24529529 | K5: 2042 | L5: 0.26596404
D7: =D5 -> 0.24161594 | F7: =F5 -> 0.39108099 | H7: =H5 -> 0.43752674 | J7: =J5 -> 0.24529529 | L7: =L5 -> 0.26596404

Sheet Campaign analysis
B3: Devices | C3: Total Orders | H3: Channel | I3: Total Quantity | J3: Total Revenue | K3: Profit Margin
B4: Desktop | C4: 68302 | H4: SEM | I4: 1573 | J4: 184874 | K4: 0.31897941
B5: Tablet | C5: 67806 | H5: Affliliate | I5: 1397 | J5: 108309 | K5: 0.20483062
B6: Mobile | C6: 63256 | H6: Email | I6: 1219 | J6: 106829 | K6: 0.2045512
B7: Laptop | C7: 13100 | H7: SMO | I7: 1689 | J7: 179192 | K7: 0.20259833
B8: Television | C8: 3649 | H8: SEO | I8: 1517 | J8: 160823 | K8: 0.198591
B9: Grand Total | C9: 216113 | H9: Organic Search | I9: 2864 | J9: 262106 | K9: 0.18456655
H10: Banner | I10: 959 | J10: 86712 | K10: 0.18316957
H11: Grand Total | I11: 11218 | J11: 1088845 | K11: 0.21629249

Sheet Product analysis
B4: Category | C4: Total Orders | G4: Products | H4: Total Units | I4: Total Revenue | J4: Profit Margin
B5: Urban | C5: 177485 | G5: Maximus UM-08 | H5: 362 | I5: 60454 | J5: 0.74850299
B6: Mix | C6: 18308 | G6: Maximus UM-11 | H6: 12 | I6: 1176 | J6: 0.45918367
B7: Accessory | C7: 11218 | G7: Maximus UM-10 | H7: 1610 | I7: 294630 | J7: 0.2295082
B8: Youth | C8: 4179 | G8: Maximus UM-07 | H8: 821 | I8: 143675 | J8: 0.20571429
B9: Rural | C9: 10 | G9: Maximus UM-12 | H9: 8413 | I9: 588910 | J9: 0.15714286
B10: Grand Total | C10: 211200 | G10: Grand Total | H10: 11218 | I10: 1088845 | J10: 0.21629249

Sheet Geography analysis
B5: States | C5: Total Revenue | F5: Total Units | G5: Region | N5: =B5 -> States | O5: =C5 -> Total Revenue
B6: Florida | C6: 85249 | F6: Channels | G6: Central | H6: East | I6: West | J6: Grand Total | N6: =B6 -> Florida | O6: =C6 -> 85249
B7: Texas | C7: 80821 | F7: Affliliate | G7: 0.41875447 | H7: 0.46313529 | I7: 0.11811024 | J7: 1 | N7: =B7 -> Texas | O7: =C7 -> 80821
B8: Ohio | C8: 69090 | F8: Banner | G8: 0.43169969 | H8: 0.4713243 | I8: 0.096976017 | J8: 1 | N8: =B8 -> Ohio | O8: =C8 -> 69090
B9: Illinois | C9: 58215 | F9: Email | G9: 0.38720263 | H9: 0.48646432 | I9: 0.12633306 | J9: 1 | N9: =B9 -> Illinois | O9: =C9 -> 58215
B10: Pennsylvania | C10: 53349 | F10: Organic Search | G10: 0.38337989 | H10: 0.49650838 | I10: 0.12011173 | J10: 1 | N10: =B10 -> Pennsylvania | O10: =C10 -> 53349
B11: Michigan | C11: 44302 | F11: SEM | G11: 0.29879212 | H11: 0.58169104 | I11: 0.11951685 | J11: 1 | N11: =B11 -> Michigan | O11: =C11 -> 44302
B12: California | C12: 43693 | F12: SEO | G12: 0.3902439 | H12: 0.50164799 | I12: 0.10810811 | J12: 1 | N12: =B12 -> California | O12: =C12 -> 43693
B13: North Carolina | C13: 40503 | F13: SMO | G13: 0.39609236 | H13: 0.47720545 | I13: 0.12670219 | J13: 1 | N13: =B13 -> North Carolina | O13: =C13 -> 40503
B14: Missouri | C14: 37971 | F14: Grand Total | G14: 0.38331253 | H14: 0.49884115 | I14: 0.11784632 | J14: 1 | N14: =B14 -> Missouri | O14: =C14 -> 37971
B15: Wisconsin | C15: 36392 | N15: =B15 -> Wisconsin | O15: =C15 -> 36392
B16: New York | C16: 34933 | N16: =B16 -> New York | O16: =C16 -> 34933
B17: Iowa | C17: 33769 | N17: =B17 -> Iowa | O17: =C17 -> 33769
B18: Virginia | C18: 32697 | N18: =B18 -> Virginia | O18: =C18 -> 32697
B19: Georgia | C19: 29937 | N19: =B19 -> Georgia | O19: =C19 -> 29937
B20: Tennessee | C20: 25862 | N20: =B20 -> Tennessee | O20: =C20 -> 25862
B21: Indiana | C21: 25611 | N21: =B21 -> Indiana | O21: =C21 -> 25611
B22: Louisiana | C22: 23467 | N22: =B22 -> Louisiana | O22: =C22 -> 23467
B23: Washington | C23: 22631 | N23: =B23 -> Washington | O23: =C23 -> 22631
B24: Arizona | C24: 22496 | N24: =B24 -> Arizona | O24: =C24 -> 22496
B25: Oklahoma | C25: 21350 | N25: =B25 -> Oklahoma | O25: =C25 -> 21350
B26: South Carolina | C26: 20124 | N26: =B26 -> South Carolina | O26: =C26 -> 20124
... B53: Grand Total | C53: 1088845 | N53: =B53 -> Grand Total | O53: =C53 -> 1088845
N54: =B54 -> 0 | O54: =C54 -> 0

Sheet Dashboard
J28: Traffic Channel Summary | Q28: Top 10 Products by Total Revenue
J29: =IF('Campaign analysis'!H3="","",'Campaign analysis'!H3) -> Channel | K29: =IF('Campaign analysis'!I3="","",'Campaign analysis'!I3) -> Total Quantity | L29: =IF('Campaign analysis'!J3="","",'Campaign analysis'!J3) -> Total Revenue | M29: =IF('Campaign analysis'!K3="","",'Campaign analysis'!K3) -> Profit Margin | Q29: =IF('Product analysis'!G4="","",'Product analysis'!G4) -> Products | R29: =IF('Product analysis'!H4="","",'Product analysis'!H4) -> Total Units | S29: =IF('Product analysis'!I4="","",'Product analysis'!I4) -> Total Revenue | T29: =IF('Product analysis'!J4="","",'Product analysis'!J4) -> Profit Margin
J30: =IF('Campaign analysis'!H4="","",'Campaign analysis'!H4) -> SEM | K30: =IF('Campaign analysis'!I4="","",'Campaign analysis'!I4) -> 1573 | L30: =IF('Campaign analysis'!J4="","",'Campaign analysis'!J4) -> 184874 | M30: =IF('Campaign analysis'!K4="","",'Campaign analysis'!K4) -> 0.31897941 | Q30: =IF('Product analysis'!G5="","",'Product analysis'!G5) -> Maximus UM-08 | R30: =IF('Product analysis'!H5="","",'Product analysis'!H5) -> 362 | S30: =IF('Product analysis'!I5="","",'Product analysis'!I5) -> 60454 | T30: =IF('Product analysis'!J5="","",'Product analysis'!J5) -> 0.74850299
J31: =IF('Campaign analysis'!H5="","",'Campaign analysis'!H5) -> Affliliate | K31: =IF('Campaign analysis'!I5="","",'Campaign analysis'!I5) -> 1397 | L31: =IF('Campaign analysis'!J5="","",'Campaign analysis'!J5) -> 108309 | M31: =IF('Campaign analysis'!K5="","",'Campaign analysis'!K5) -> 0.20483062 | Q31: =IF('Product analysis'!G6="","",'Product analysis'!G6) -> Maximus UM-11 | R31: =IF('Product analysis'!H6="","",'Product analysis'!H6) -> 12 | S31: =IF('Product analysis'!I6="","",'Product analysis'!I6) -> 1176 | T31: =IF('Product analysis'!J6="","",'Product analysis'!J6) -> 0.45918367
J32: =IF('Campaign analysis'!H6="","",'Campaign analysis'!H6) -> Email | K32: =IF('Campaign analysis'!I6="","",'Campaign analysis'!I6) -> 1219 | L32: =IF('Campaign analysis'!J6="","",'Campaign analysis'!J6) -> 106829 | M32: =IF('Campaign analysis'!K6="","",'Campaign analysis'!K6) -> 0.2045512 | Q32: =IF('Product analysis'!G7="","",'Product analysis'!G7) -> Maximus UM-10 | R32: =IF('Product analysis'!H7="","",'Product analysis'!H7) -> 1610 | S32: =IF('Product analysis'!I7="","",'Product analysis'!I7) -> 294630 | T32: =IF('Product analysis'!J7="","",'Product analysis'!J7) -> 0.2295082
J33: =IF('Campaign analysis'!H7="","",'Campaign analysis'!H7) -> SMO | K33: =IF('Campaign analysis'!I7="","",'Campaign analysis'!I7) -> 1689 | L33: =IF('Campaign analysis'!J7="","",'Campaign analysis'!J7) -> 179192 | M33: =IF('Campaign analysis'!K7="","",'Campaign analysis'!K7) -> 0.20259833 | Q33: =IF('Product analysis'!G8="","",'Product analysis'!G8) -> Maximus UM-07 | R33: =IF('Product analysis'!H8="","",'Product analysis'!H8) -> 821 | S33: =IF('Product analysis'!I8="","",'Product analysis'!I8) -> 143675 | T33: =IF('Product analysis'!J8="","",'Product analysis'!J8) -> 0.20571429
J34: =IF('Campaign analysis'!H8="","",'Campaign analysis'!H8) -> SEO | K34: =IF('Campaign analysis'!I8="","",'Campaign analysis'!I8) -> 1517 | L34: =IF('Campaign analysis'!J8="","",'Campaign analysis'!J8) -> 160823 | M34: =IF('Campaign analysis'!K8="","",'Campaign analysis'!K8) -> 0.198591 | Q34: =IF('Product analysis'!G9="","",'Product analysis'!G9) -> Maximus UM-12 | R34: =IF('Product analysis'!H9="","",'Product analysis'!H9) -> 8413 | S34: =IF('Product analysis'!I9="","",'Product analysis'!I9) -> 588910 | T34: =IF('Product analysis'!J9="","",'Product analysis'!J9) -> 0.15714286
J35: =IF('Campaign analysis'!H9="","",'Campaign analysis'!H9) -> Organic Search | K35: =IF('Campaign analysis'!I9="","",'Campaign analysis'!I9) -> 2864 | L35: =IF('Campaign analysis'!J9="","",'Campaign analysis'!J9) -> 262106 | M35: =IF('Campaign analysis'!K9="","",'Campaign analysis'!K9) -> 0.18456655 | Q35: =IF('Product analysis'!G10="","",'Product analysis'!G10) -> Grand Total | R35: =IF('Product analysis'!H10="","",'Product analysis'!H10) -> 11218 | S35: =IF('Product analysis'!I10="","",'Product analysis'!I10) -> 1088845 | T35: =IF('Product analysis'!J10="","",'Product analysis'!J10) -> 0.21629249
J36: =IF('Campaign analysis'!H10="","",'Campaign analysis'!H10) -> Banner | K36: =IF('Campaign analysis'!I10="","",'Campaign analysis'!I10) -> 959 | L36: =IF('Campaign analysis'!J10="","",'Campaign analysis'!J10) -> 86712 | M36: =IF('Campaign analysis'!K10="","",'Campaign analysis'!K10) -> 0.18316957 | Q36: =IF('Product analysis'!G11="","",'Product analysis'!G11) | R36: =IF('Product analysis'!H11="","",'Product analysis'!H11) | S36: =IF('Product analysis'!I11="","",'Product analysis'!I11) | T36: =IF('Product analysis'!J11="","",'Product analysis'!J11)
J37: =IF('Campaign analysis'!H11="","",'Campaign analysis'!H11) -> Grand Total | K37: =IF('Campaign analysis'!I11="","",'Campaign analysis'!I11) -> 11218 | L37: =IF('Campaign analysis'!J11="","",'Campaign analysis'!J11) -> 1088845 | M37: =IF('Campaign analysis'!K11="","",'Campaign analysis'!K11) -> 0.21629249 | Q37: =IF('Product analysis'!G12="","",'Product analysis'!G12) | R37: =IF('Product analysis'!H12="","",'Product analysis'!H12) | S37: =IF('Product analysis'!I12="","",'Product analysis'!I12) | T37: =IF('Product analysis'!J12="","",'Product analysis'!J12)
J38: =IF('Campaign analysis'!H12="","",'Campaign analysis'!H12) | K38: =IF('Campaign analysis'!I12="","",'Campaign analysis'!I12) | L38: =IF('Campaign analysis'!J12="","",'Campaign analysis'!J12) | M38: =IF('Campaign analysis'!K12="","",'Campaign analysis'!K12) | Q38: =IF('Product analysis'!G13="","",'Product analysis'!G13) | R38: =IF('Product analysis'!H13="","",'Product analysis'!H13) | S38: =IF('Product analysis'!I13="","",'Product analysis'!I13) | T38: =IF('Product analysis'!J13="","",'Product analysis'!J13)
Q39: =IF('Product analysis'!G14="","",'Product analysis'!G14) | R39: =IF('Product analysis'!H14="","",'Product analysis'!H14) | S39: =IF('Product analysis'!I14="","",'Product analysis'!I14) | T39: =IF('Product analysis'!J14="","",'Product analysis'!J14)
Q40: =IF('Product analysis'!G15="","",'Product analysis'!G15) | R40: =IF('Product analysis'!H15="","",'Product analysis'!H15) | S40: =IF('Product analysis'!I15="","",'Product analysis'!I15) | T40: =IF('Product analysis'!J15="","",'Product analysis'!J15)

Sheet Dashboard (2)
J28: Traffic Channel Summary | Q28: Top 10 Products by Total Revenue
J29: =IF('Campaign analysis'!H3="","",'Campaign analysis'!H3) -> Channel | K29: =IF('Campaign analysis'!I3="","",'Campaign analysis'!I3) -> Total Quantity | L29: =IF('Campaign analysis'!J3="","",'Campaign analysis'!J3) -> Total Revenue | M29: =IF('Campaign analysis'!K3="","",'Campaign analysis'!K3) -> Profit Margin | Q29: =IF('Product analysis'!G4="","",'Product analysis'!G4) -> Products | R29: =IF('Product analysis'!H4="","",'Product analysis'!H4) -> Total Units | S29: =IF('Product analysis'!I4="","",'Product analysis'!I4) -> Total Revenue | T29: =IF('Product analysis'!J4="","",'Product analysis'!J4) -> Profit Margin
J30: =IF('Campaign analysis'!H4="","",'Campaign analysis'!H4) -> SEM | K30: =IF('Campaign analysis'!I4="","",'Campaign analysis'!I4) -> 1573 | L30: =IF('Campaign analysis'!J4="","",'Campaign analysis'!J4) -> 184874 | M30: =IF('Campaign analysis'!K4="","",'Campaign analysis'!K4) -> 0.31897941 | Q30: =IF('Product analysis'!G5="","",'Product analysis'!G5) -> Maximus UM-08 | R30: =IF('Product analysis'!H5="","",'Product analysis'!H5) -> 362 | S30: =IF('Product analysis'!I5="","",'Product analysis'!I5) -> 60454 | T30: =IF('Product analysis'!J5="","",'Product analysis'!J5) -> 0.74850299
J31: =IF('Campaign analysis'!H5="","",'Campaign analysis'!H5) -> Affliliate | K31: =IF('Campaign analysis'!I5="","",'Campaign analysis'!I5) -> 1397 | L31: =IF('Campaign analysis'!J5="","",'Campaign analysis'!J5) -> 108309 | M31: =IF('Campaign analysis'!K5="","",'Campaign analysis'!K5) -> 0.20483062 | Q31: =IF('Product analysis'!G6="","",'Product analysis'!G6) -> Maximus UM-11 | R31: =IF('Product analysis'!H6="","",'Product analysis'!H6) -> 12 | S31: =IF('Product analysis'!I6="","",'Product analysis'!I6) -> 1176 | T31: =IF('Product analysis'!J6="","",'Product analysis'!J6) -> 0.45918367
J32: =IF('Campaign analysis'!H6="","",'Campaign analysis'!H6) -> Email | K32: =IF('Campaign analysis'!I6="","",'Campaign analysis'!I6) -> 1219 | L32: =IF('Campaign analysis'!J6="","",'Campaign analysis'!J6) -> 106829 | M32: =IF('Campaign analysis'!K6="","",'Campaign analysis'!K6) -> 0.2045512 | Q32: =IF('Product analysis'!G7="","",'Product analysis'!G7) -> Maximus UM-10 | R32: =IF('Product analysis'!H7="","",'Product analysis'!H7) -> 1610 | S32: =IF('Product analysis'!I7="","",'Product analysis'!I7) -> 294630 | T32: =IF('Product analysis'!J7="","",'Product analysis'!J7) -> 0.2295082
J33: =IF('Campaign analysis'!H7="","",'Campaign analysis'!H7) -> SMO | K33: =IF('Campaign analysis'!I7="","",'Campaign analysis'!I7) -> 1689 | L33: =IF('Campaign analysis'!J7="","",'Campaign analysis'!J7) -> 179192 | M33: =IF('Campaign analysis'!K7="","",'Campaign analysis'!K7) -> 0.20259833 | Q33: =IF('Product analysis'!G8="","",'Product analysis'!G8) -> Maximus UM-07 | R33: =IF('Product analysis'!H8="","",'Product analysis'!H8) -> 821 | S33: =IF('Product analysis'!I8="","",'Product analysis'!I8) -> 143675 | T33: =IF('Product analysis'!J8="","",'Product analysis'!J8) -> 0.20571429
J34: =IF('Campaign analysis'!H8="","",'Campaign analysis'!H8) -> SEO | K34: =IF('Campaign analysis'!I8="","",'Campaign analysis'!I8) -> 1517 | L34: =IF('Campaign analysis'!J8="","",'Campaign analysis'!J8) -> 160823 | M34: =IF('Campaign analysis'!K8="","",'Campaign analysis'!K8) -> 0.198591 | Q34: =IF('Product analysis'!G9="","",'Product analysis'!G9) -> Maximus UM-12 | R34: =IF('Product analysis'!H9="","",'Product analysis'!H9) -> 8413 | S34: =IF('Product analysis'!I9="","",'Product analysis'!I9) -> 588910 | T34: =IF('Product analysis'!J9="","",'Product analysis'!J9) -> 0.15714286
J35: =IF('Campaign analysis'!H9="","",'Campaign analysis'!H9) -> Organic Search | K35: =IF('Campaign analysis'!I9="","",'Campaign analysis'!I9) -> 2864 | L35: =IF('Campaign analysis'!J9="","",'Campaign analysis'!J9) -> 262106 | M35: =IF('Campaign analysis'!K9="","",'Campaign analysis'!K9) -> 0.18456655 | Q35: =IF('Product analysis'!G10="","",'Product analysis'!G10) -> Grand Total | R35: =IF('Product analysis'!H10="","",'Product analysis'!H10) -> 11218 | S35: =IF('Product analysis'!I10="","",'Product analysis'!I10) -> 1088845 | T35: =IF('Product analysis'!J10="","",'Product analysis'!J10) -> 0.21629249
J36: =IF('Campaign analysis'!H10="","",'Campaign analysis'!H10) -> Banner | K36: =IF('Campaign analysis'!I10="","",'Campaign analysis'!I10) -> 959 | L36: =IF('Campaign analysis'!J10="","",'Campaign analysis'!J10) -> 86712 | M36: =IF('Campaign analysis'!K10="","",'Campaign analysis'!K10) -> 0.18316957 | Q36: =IF('Product analysis'!G11="","",'Product analysis'!G11) | R36: =IF('Product analysis'!H11="","",'Product analysis'!H11) | S36: =IF('Product analysis'!I11="","",'Product analysis'!I11) | T36: =IF('Product analysis'!J11="","",'Product analysis'!J11)
J37: =IF('Campaign analysis'!H11="","",'Campaign analysis'!H11) -> Grand Total | K37: =IF('Campaign analysis'!I11="","",'Campaign analysis'!I11) -> 11218 | L37: =IF('Campaign analysis'!J11="","",'Campaign analysis'!J11) -> 1088845 | M37: =IF('Campaign analysis'!K11="","",'Campaign analysis'!K11) -> 0.21629249 | Q37: =IF('Product analysis'!G12="","",'Product analysis'!G12) | R37: =IF('Product analysis'!H12="","",'Product analysis'!H12) | S37: =IF('Product analysis'!I12="","",'Product analysis'!I12) | T37: =IF('Product analysis'!J12="","",'Product analysis'!J12)
J38: =IF('Campaign analysis'!H12="","",'Campaign analysis'!H12) | K38: =IF('Campaign analysis'!I12="","",'Campaign analysis'!I12) | L38: =IF('Campaign analysis'!J12="","",'Campaign analysis'!J12) | M38: =IF('Campaign analysis'!K12="","",'Campaign analysis'!K12) | Q38: =IF('Product analysis'!G13="","",'Product analysis'!G13) | R38: =IF('Product analysis'!H13="","",'Product analysis'!H13) | S38: =IF('Product analysis'!I13="","",'Product analysis'!I13) | T38: =IF('Product analysis'!J13="","",'Product analysis'!J13)
Q39: =IF('Product analysis'!G14="","",'Product analysis'!G14) | R39: =IF('Product analysis'!H14="","",'Product analysis'!H14) | S39: =IF('Product analysis'!I14="","",'Product analysis'!I14) | T39: =IF('Product analysis'!J14="","",'Product analysis'!J14)
Q40: =IF('Product analysis'!G15="","",'Product analysis'!G15) | R40: =IF('Product analysis'!H15="","",'Product analysis'!H15) | S40: =IF('Product analysis'!I15="","",'Product analysis'!I15) | T40: =IF('Product analysis'!J15="","",'Product analysis'!J15)
